socialagent/__init__.py
socialagent/socialagent.py
socialagent-0.9.dist-info/LICENSE
socialagent-0.9.dist-info/METADATA
socialagent-0.9.dist-info/WHEEL
socialagent-0.9.dist-info/top_level.txt
socialagent-0.9.dist-info/RECORD
