Metadata-Version: 2.1
Name: socialagent
Version: 0.9
Summary: socialagent is a Python module designed for generating user agents specific to social media platforms under Meta (formerly Facebook).
Home-page: https://github.com/iqbalmh18/socialagent
Author: Moh Iqbal Hidayat
Author-email: iqbalmh18.dev@gmail.com
Classifier: Programming Language :: Python :: 3
Classifier: License :: OSI Approved :: MIT License
Classifier: Operating System :: OS Independent
Requires-Python: >=3.6
License-File: LICENSE
